sketchpy_mob/__init__.py
sketchpy_mob/canvas.py
sketchpy_mob/library.py
sketchpy_mob-0.0.2.dist-info/METADATA
sketchpy_mob-0.0.2.dist-info/WHEEL
sketchpy_mob-0.0.2.dist-info/top_level.txt
sketchpy_mob-0.0.2.dist-info/RECORD
