Metadata-Version: 2.1
Name: sketchpy-mob
Version: 0.0.2
Summary: sketchpy mobile version
Author: Mr Mystery
Author-email: sriramanand23@gmail.com
License: UNKNOWN
Keywords: python,sketch,drawing,animation,code hub,pencil sketch,painting
Platform: UNKNOWN
Classifier: Development Status :: 1 - Planning
Classifier: Intended Audience :: Developers
Classifier: Programming Language :: Python :: 3
Classifier: Operating System :: Unix
Classifier: Operating System :: MacOS :: MacOS X
Classifier: Operating System :: Microsoft :: Windows
Requires-Dist: turtle (==0.0.1)
Requires-Dist: wheel
Requires-Dist: svg.path
Requires-Dist: svgpathtools
Requires-Dist: tqdm
